pkg1/__init__.py
pkg1/validate.py
pkg2/__init__.py
pkg2/calculator.py
tests/__init__.py
tests/test_validate.py
pyplbasicpkg-1.0.0.dist-info/LICENSE.txt
pyplbasicpkg-1.0.0.dist-info/METADATA
pyplbasicpkg-1.0.0.dist-info/WHEEL
pyplbasicpkg-1.0.0.dist-info/top_level.txt
pyplbasicpkg-1.0.0.dist-info/RECORD
