Metadata-Version: 2.1
Name: pyplbasicpkg
Version: 1.0.0
Summary: A simple Python package
Home-page: UNKNOWN
Author: balu2012
Author-email: baluthota2012@gmai.com
License: UNKNOWN
Platform: UNKNOWN
Classifier: Programming Language :: Python :: 3
Classifier: License :: OSI Approved :: MIT License
Classifier: Operating System :: OS Independent
Requires-Python: >=3.6
License-File: LICENSE.txt
